linksaas_events_py/__init__.py
linksaas_events_py/project_book_shelf_events.py
linksaas_events_py/project_doc_events.py
linksaas_events_py/project_earthly_events.py
linksaas_events_py/project_events.py
linksaas_events_py/project_ext_event_events.py
linksaas_events_py/project_gitee_events.py
linksaas_events_py/project_gitlab_events.py
linksaas_events_py/project_issue_event.py
linksaas_events_py/project_robot_events.py
linksaas_events_py/project_sprit_events.py
linksaas_events_py-0.0.3.dist-info/METADATA
linksaas_events_py-0.0.3.dist-info/WHEEL
linksaas_events_py-0.0.3.dist-info/top_level.txt
linksaas_events_py-0.0.3.dist-info/RECORD
