Metadata-Version: 2.1
Name: linksaas-events-py
Version: 0.0.3
Summary: struct define for linksaas events
Author-email: panleiming <panleiming@linksaas.pro>
Project-URL: Homepage, https://jihulab.com/linksaas/analysis/events_py
Classifier: Development Status :: 3 - Alpha
Classifier: Environment :: Other Environment
Classifier: License :: Freeware
Classifier: Programming Language :: Python :: 3
Classifier: Topic :: Utilities
Classifier: Typing :: Typed
Requires-Python: >=3.6
